{
  "cid": 10886,
  "FAQ": {
    "": [],
    "1": [
      "『①：自分メインフェイズに発動できる。自分のデッキの上からカードを２枚墓地へ送る。この効果で墓地へ送ったカードの中に「ライトロード」モンスターがあった場合、さらにこのカードの攻撃力は相手ターン終了時まで２００アップする』モンスター効果は起動効果です。",
      "『自分のデッキの上からカードを２枚墓地へ送る』処理と『この効果で墓地へ送ったカードの中に「ライトロード」モンスターがあった場合、さらにこのカードの攻撃力は相手ターン終了時まで２００アップする』処理は同時に行われる扱いではありません。（墓地へ送ったカードの中に「ライトロード」と名のついたモンスターがなかった場合には、『自分のデッキの上からカードを２枚墓地へ送る』処理にて処理が完了した扱いとなります。）"
    ],
    "2": [
      "『②：自分エンドフェイズに発動する。自分のデッキの上からカードを２枚墓地へ送る』モンスター効果は誘発効果です。（対象を取る効果ではありません。エンドフェイズに1度のみ、必ず発動する効果です。）",
      "『自分エンドフェイズに発動する。自分のデッキの上からカードを２枚墓地へ送る』モンスター効果は、自分のエンドフェイズに自分のデッキの枚数が1枚の場合でも発動します。（その場合、その1枚を墓地へ送る処理を行います。）"
    ]
  },
  "pendulumFAQ": []
}
