{
  "cid": 11184,
  "FAQ": {
    "": [],
    "0.5": [
      "【『自分の墓地のレベル１０以上の機械族モンスター２体を除外して発動した場合のみ、機械族・地属性モンスターに装備可能』について】",
      "効果として扱いません。このカードを装備する条件です。",
      "このカードを発動する際に、自分の墓地のレベル１０以上の機械族モンスター２体を除外します。",
      "この方法以外の方法で、このカードを装備させることははできません。"
    ],
    "1": [
      "【①の効果について】",
      "魔法＆罠ゾーンの表側表示のこのカードが適用するチェーンブロックの作られない効果です。",
      "装備モンスターに適用される効果です。"
    ],
    "2": [
      "【②の効果について】",
      "魔法＆罠ゾーンの表側表示のこのカードが適用するチェーンブロックの作られない効果です。",
      "装備モンスター以外の自分のモンスターに適用される効果です。"
    ]
  },
  "pendulumFAQ": []
}
