{
  "cid": 11825,
  "databaseDate": "2019-03-09",
  "FAQ": {
    "0": [],
    "0.5": [
      "【①のモンスター効果について】",
      "モンスターゾーンで適用する永続効果です。",
      "魔力カウンターを置く処理にチェーンブロックは作られません。",
      "ダメージステップでも適用します。"
    ],
    "0.75": [
      "【②のモンスター効果について】",
      "モンスターゾーンで適用する永続効果です。",
      "このモンスター自身に置かれている魔力カウンターの数が変化する度に、アップする攻撃力の数値も変化します。"
    ],
    "0.875": [
      "【③のモンスター効果について】",
      "モンスターゾーンで発動できる起動効果です。",
      "この効果を発動する際にコストとして、このカードに置かれている魔力カウンターを３つ取り除きます。"
    ]
  },
  "pendulumFAQ": {
    "0": [],
    "1": [
      "【①のペンデュラム効果について】",
      "ペンデュラムゾーンで適用するチェーンブロックの作られない効果です。（魔力カウンターを置く処理にもチェーンブロックは作られません。）",
      "ダメージステップでも適用します。"
    ],
    "2": [
      "【②のペンデュラム効果について】",
      "ペンデュラムゾーンで発動できるチェーンブロックの作られる効果です。",
      "自分のメインフェイズにのみ発動できます。",
      "このペンデュラム効果を発動する際にコストとして、このカードに置かれている魔力カウンターを３つ取り除きます。",
      "処理時に、このカードがペンデュラムゾーンに存在しない場合、処理は何も行われません。"
    ]
  },
  "listedQAs": [
    9496,
    15628,
    15631,
    15632,
    15635
  ]
}
