{
  "cid": 12908,
  "databaseDate": "2024-02-23",
  "FAQ": {
    "0": [],
    "0.5": [
      "【『このカードはルール上「ペンデュラム・ドラゴン」カードとしても扱う』について】",
      "効果として扱いません。（効果が無効化されている状況でも「ペンデュラム・ドラゴン」カードとして扱われます。）",
      "「ペンデュラム」カードとしても扱います。"
    ],
    "1": [
      "【①の効果について】",
      "誘発効果です。",
      "どこで破壊された場合でも発動できます。",
      "破壊され、エクストラデッキに表側で加わった場合にはエクストラデッキで、表側で除外された場合には除外状態で、墓地へ送られた場合には墓地で発動できます。（破壊され最初に送られたところで発動できます。）",
      "ダメージステップ中に条件を満たした場合でも発動できます。"
    ]
  },
  "pendulumFAQ": {
    "0": [],
    "1": [
      "【①の効果について】",
      "ペンデュラムゾーンで発動できるチェーンブロックの作られる効果です。",
      "先攻１ターン目やメインフェイズ２、カードの効果によりバトルフェイズを行うことができないターンにはこの効果を発動できません。",
      "処理時に、対象のモンスターが裏側守備表示になっている場合でも『●』の効果を適用します。（そのターン中にリバースして攻撃表示に戻った場合、相手モンスターとの戦闘で相手に与える戦闘ダメージは倍になります。）",
      "処理時に、対象のモンスターがモンスターゾーンに存在しない場合、処理は何も行われません。",
      "処理時に、対象のモンスターがこの効果を受けない場合でも、『●』の効果は適用され、その後このカードを破壊します。（『●』の効果は対象のモンスターに適用する効果ではありません。）"
    ]
  },
  "listedQAs": [
    8634,
    9936,
    20423,
    20429,
    20584
  ]
}
