{
  "cid": 12967,
  "databaseDate": "2017-01-14",
  "FAQ": {
    "0": [],
    "1": [
      "【①の効果について】",
      "チェーンブロックの作られない効果です。（お互いの「真竜」と名のついたモンスターに適用されます。魔法カードの効果を受けない「真竜」モンスターには適用されません。）"
    ],
    "2": [
      "【②の効果について】",
      "チェーンブロックの作られない効果です。（アドバンス召喚された、お互いの「真竜」と名のついたモンスターに適用されます。魔法カードの効果を受けない「真竜」と名のついたモンスターには適用されません。）",
      "アドバンス召喚した「真竜」モンスターが一時的に除外されフィールドに戻った場合でも、この効果がそのモンスターに適用されます。",
      "アドバンス召喚した「真竜」モンスターが一度裏側守備表示になり、再び表側表示になった場合でも、この効果がそのモンスターに適用されます。"
    ],
    "3": [
      "【③の効果について】",
      "チェーンブロックの作られる効果です。（対象を取る効果ではありません。）",
      "このカードのコントローラーのみが、この効果を発動できます。",
      "『このカード以外の自分の手札・フィールドのカード１枚を選んで破壊』する処理に成功した場合、『デッキから「真竜」カード１枚を手札に加える』処理が行われます。（これらは同時に行われたものとして扱います。）"
    ]
  },
  "pendulumFAQ": {},
  "listedQAs": [
    7634,
    8574,
    20533
  ]
}
