{
  "cid": 13863,
  "FAQ": {
    "": [],
    "1": [
      "『①：このカードの戦闘で発生する自分への戦闘ダメージは０になる』モンスター効果は永続効果です。"
    ],
    "2": [
      "『②：自分スタンバイフェイズに発動する。このカードのコントロールを相手に移す』モンスター効果は誘発効果です。（対象を取る効果ではありません。）"
    ],
    "3": [
      "『③：１ターンに１度、このカードのコントロールが移った場合に発動する。このカードの元々の持ち主は自身の魔法＆罠ゾーンにセットされた「魔界台本」魔法カード１枚を選んで破壊できる』モンスター効果は誘発効果です。（対象を取る効果ではありません。）"
    ]
  },
  "pendulumFAQ": {
    "": [],
    "1": [
      "『①：相手フィールドのモンスター１体と自分フィールドの「魔界劇団」Pモンスター１体を対象として発動できる。そのモンスター２体のコントロールを入れ替える。その後、このカードを破壊する』ペンデュラム効果は、チェーンブロックの作られる効果です。（自分のメインフェイズにのみ発動する事ができます。）",
      "相手のモンスターゾーンに存在するモンスター1体と、自分のモンスターゾーンに表側表示で存在する「魔界劇団」と名のついたペンデュラムモンスター1体、合計2体のモンスターを対象に取る効果です。",
      "『そのモンスター２体のコントロールを入れ替える』処理と、『その後、このカードを破壊する』処理は同時に行われる扱いではありません。"
    ]
  }
}
