{
  "cid": 13865,
  "databaseDate": "2018-06-09",
  "FAQ": {
    "0": [],
    "1": [
      "【①の効果について】",
      "チェーンブロックの作られる効果です。（自分メインフェイズにのみ発動できます。）",
      "この効果を発動する際のコストとして、自分の手札の「魔界劇団」と名のついたペンデュラムモンスター１体と、「魔界台本」と名のついた魔法カード１枚、合計２枚のカードを相手に見せます。"
    ],
    "2": [
      "【②の効果について】",
      "チェーンブロックの作られない効果です。",
      "モンスターに適用する効果ではありません。(魔法カードの効果を受けない状態のモンスターの効果も、『相手フィールドにセットされた魔法・罠カード１枚を選んで破壊する』に変更されます。)"
    ]
  },
  "pendulumFAQ": {},
  "listedQAs": [
    7934,
    10412,
    10420,
    20559,
    21934
  ]
}
