{
  "cid": 13871,
  "FAQ": {
    "": [],
    "1": [
      "『①：手札からこのカード以外のサイバース族モンスター１体を捨てて発動できる。このカードを手札から特殊召喚する』モンスター効果は、手札にて発動する起動効果です。（対象を取る効果ではありません。）",
      "『このカードを手札から特殊召喚する』モンスター効果を発動する際に、コストとして、「デフコンバード」自身を除く、自分の手札のサイバース族モンスター1体を捨てます。"
    ],
    "2": [
      "『②：１ターンに１度、自分のサイバース族モンスターが攻撃対象に選択された時に発動できる。そのモンスターの攻撃力・守備力はそのダメージステップ終了時まで元々の攻撃力の倍になる。そのモンスターが攻撃表示の場合、さらにその表示形式を守備表示にできる』モンスター効果は誘発効果です。（対象を取る効果ではありません。）",
      "『そのモンスターの攻撃力・守備力はそのダメージステップ終了時まで元々の攻撃力の倍になる』処理と、『そのモンスターが攻撃表示の場合、さらにその表示形式を守備表示にできる』処理は同時に行われる扱いではありません。",
      "『そのモンスターの攻撃力・守備力はそのダメージステップ終了時まで元々の攻撃力の倍になる』処理は必ず行いますが、『そのモンスターが攻撃表示の場合、さらにその表示形式を守備表示にできる』処理は行わないとする事もできます。"
    ]
  },
  "pendulumFAQ": []
}
