{
  "cid": 13890,
  "databaseDate": "2018-07-14",
  "FAQ": {
    "0": [],
    "1": [
      "『①：このカードが召喚に成功した時に発動できる。自分のデッキの上からカードを３枚めくる。その中から「サラマングレイト」カード１枚を選んで手札に加える事ができる。残りのカードはデッキに戻す』モンスター効果は誘発効果です。（対象を取る効果ではありません。）",
      "『自分のデッキの上からカードを３枚めくる』処理によってめくったカードの中に、「サラマングレイト」と名のついたカードがあった場合でも、手札に加えずデッキに戻す事もできます。（その場合、めくったカードを全てデッキに戻す事になります。）"
    ],
    "2": [
      "『②：このカードが墓地に存在し、フィールドに表側表示の魔法・罠カードが存在する場合、手札から「サラマングレイト」カード１枚を捨てて発動できる。このカードを特殊召喚する。その後、フィールドの表側表示の魔法・罠カード１枚を選んで破壊できる』モンスター効果は、墓地にて発動する起動効果です。（対象を取る効果ではありません。この効果を発動する際に、コストとして、「サラマングレイト」と名のついたカード1枚を手札から捨てます。）",
      "『このカードを特殊召喚する』処理と、『その後、フィールドの表側表示の魔法・罠カード１枚を選んで破壊できる』処理は同時に行われる扱いではありません。",
      "『このカードを特殊召喚する』処理は必ず行いますが、『その後、フィールドの表側表示の魔法・罠カード１枚を選んで破壊できる』処理は行わないとする事もできます。"
    ]
  },
  "pendulumFAQ": {},
  "listedQAs": []
}
