{
  "cid": 13975,
  "databaseDate": "2018-05-23",
  "FAQ": {
    "0": [],
    "0.5": [
      "【『このカードは通常召喚できない。「終焉龍 カオス・エンペラー」は１ターンに１度、自分の墓地の光属性と闇属性のモンスターを１体ずつ除外した場合のみ、手札・EXデッキから特殊召喚できる』について】",
      "効果として扱いません。このモンスターを手札・エクストラデッキから特殊召喚する方法・手順です。",
      "この方法による特殊召喚を行う際にチェーンブロックは作られません。",
      "除外する処理と特殊召喚は同時に行われません。",
      "原則として、この方法でしか特殊召喚できません。（ペンデュラム召喚によって特殊召喚することもできません。）"
    ],
    "0.75": [
      "【①のモンスター効果について】",
      "モンスターゾーンで発動できる起動効果です。",
      "対象を取る効果ではありません。",
      "この効果を発動する際にコストとして、自分のライフポイントを半分払います。",
      "処理時に、『EXモンスターゾーン以外の自分フィールドのカードを全て墓地へ送り』の処理を行います。１枚以上のカードを墓地に送ることに成功した場合、『墓地へ送った数まで相手フィールドのカードを選んで墓地へ送る』処理が行われます。これらは同時に行われる扱いです。",
      "『相手フィールドのカードを選んで墓地へ送る』処理によって、１枚以上のカードを墓地に送ることに成功した場合、『その後、相手の墓地へ送った数×３００ダメージを相手に与える』処理が行われます。これらは同時に行われません。",
      "処理時に、相手フィールドにカードが１枚も存在しない場合、『EXモンスターゾーン以外の自分フィールドのカードを全て墓地へ送り』の処理は行われます。",
      "相手フィールドにカードが１枚も存在しない場合、この効果は発動できません。"
    ],
    "0.875": [
      "【②のモンスター効果について】",
      "起動効果・誘発効果・誘発即時効果・永続効果のいずれにも分類されない効果です。",
      "ダメージステップでも適用されます。"
    ]
  },
  "pendulumFAQ": {
    "0": [],
    "1": [
      "【①のペンデュラム効果について】",
      "ペンデュラムゾーンで発動できるチェーンブロックの作られる効果です。",
      "自分メインフェイズに発動できます。",
      "自分の除外状態（表側）のドラゴン族モンスター１体を対象に取る効果です。",
      "この効果を発動する際のコストとして、１０００ライフポイントを払います。",
      "『このカードを破壊』する処理に成功した場合、『そのモンスターを手札に加える』処理が行われます。これらは同時に行われる扱いです。"
    ]
  },
  "listedQAs": [
    11511,
    12471,
    21915,
    21916
  ]
}
