{
  "cid": 14182,
  "databaseDate": "2020-02-08",
  "FAQ": {
    "0": [],
    "1": [
      "【①の効果について】",
      "モンスターゾーンで発動できる誘発効果です。",
      "ダメージステップでも発動できます。"
    ],
    "2": [
      "【②の効果について】",
      "モンスターゾーンで発動できる起動効果です。",
      "この効果を発動する際に、自分のモンスターゾーンに表側表示で存在する、このカード以外のモンスター１体を対象に選択します。",
      "処理時に、２体のモンスターのレベルをこのカードと同じにするか、２体のモンスターのレベルを対象のモンスターと同じにします。",
      "この効果を発動したターンには、自分はエクシーズモンスターでしか攻撃宣言できません。また、既に自分がエクシーズモンスター以外のモンスターで攻撃宣言したターンには、この効果を発動できません。"
    ]
  },
  "pendulumFAQ": {},
  "listedQAs": [
    11744,
    22227,
    22228,
    23896
  ]
}
