{
  "cid": 14245,
  "databaseDate": "2018-12-08",
  "FAQ": {
    "0": [
      "「転生炎獣の烈爪」は、自分のモンスターゾーンに表側表示で存在する「サラマングレイト」と名のついたモンスター、相手のモンスターゾーンに表側表示で存在する「サラマングレイト」と名のついたモンスターのどちらにも装備させる事ができます。"
    ],
    "1": [
      "『①：「転生炎獣の烈爪」は自分フィールドに１枚しか表側表示で存在できない』効果はチェーンブロックの作られない効果です。"
    ],
    "2": [
      "『②：装備モンスターは、戦闘・効果では破壊されず、守備表示モンスターを攻撃した場合、その守備力を攻撃力が超えた分だけ相手に戦闘ダメージを与える』効果はチェーンブロックの作られない効果です。（装備モンスターに適用される効果です。）"
    ],
    "3": [
      "『③：装備モンスターが自身と同名のモンスターを素材としてリンク召喚した自分の「サラマングレイト」リンクモンスターの場合、装備モンスターは１度のバトルフェイズ中にそのリンクマーカーの数までモンスターに攻撃できる』効果はチェーンブロックの作られない効果です。（装備モンスターに適用される効果です。）"
    ]
  },
  "pendulumFAQ": {},
  "listedQAs": [
    13613,
    22312
  ]
}
