{
  "cid": 14361,
  "databaseDate": "2019-09-14",
  "FAQ": {
    "0": [
      "このカードを発動する際に、コストとして、1000の倍数のLPを払います。",
      "払ったLP1000につき1体、自分の墓地に存在する「ワルキューレ」と名のついたモンスターを対象に取る効果です。（2体以上の「ワルキューレ」と名のついたモンスターを対象に取る場合には、同名カードは1枚までとなるように選択します。）",
      "『そのモンスターを特殊召喚する』処理と、『その後、この効果で特殊召喚したモンスターの数まで、相手は自身の墓地から攻撃力２０００以下のモンスターを選んで特殊召喚できる』処理は同時に行われる扱いではありません。",
      "『相手は自身の墓地から攻撃力２０００以下のモンスターを選んで特殊召喚できる』処理を行うかどうかは、効果処理時に相手プレイヤーが選びます。（相手が特殊召喚を行わない場合には、『そのモンスターを特殊召喚する』処理にて完了した扱いとなります。）"
    ]
  },
  "pendulumFAQ": {},
  "listedQAs": [
    22807,
    22819
  ]
}
