{
  "cid": 14450,
  "databaseDate": "2019-04-13",
  "FAQ": {
    "0": [],
    "1": [
      "『①：自分フィールドにリンクモンスターが２体以上存在する場合に発動できる。このカードを手札から特殊召喚する』モンスター効果は、手札にて発動する起動効果です。（対象を取る効果ではありません。）"
    ],
    "2": [
      "『②：自分と相手のリンクモンスター同士が戦闘を行うダメージ計算時に、墓地のこのカードを除外し、自分の墓地のリンクモンスター１体を対象として発動できる。その戦闘を行う自分のモンスターの攻撃力はターン終了時まで対象のモンスターの攻撃力分アップし、その戦闘では破壊されない』モンスター効果は、墓地にて発動する誘発即時効果です。（この効果を発動する際に、コストとして、墓地の「クロス・デバッガー」自身を除外します。）",
      "『その戦闘を行う自分のモンスターの攻撃力はターン終了時まで対象のモンスターの攻撃力分アップし、その戦闘では破壊されない』モンスター効果は、自分の墓地に存在するリンクモンスター1体を対象に取る効果です。",
      "『その戦闘を行う自分のモンスターの攻撃力はターン終了時まで対象のモンスターの攻撃力分アップし、その戦闘では破壊されない』モンスター効果が適用された場合、攻撃力のアップはターン終了時まで適用されますが、戦闘で破壊されないのは、効果を発動したそのダメージ計算時の戦闘の1度のみとなります。"
    ]
  },
  "pendulumFAQ": {},
  "listedQAs": [
    22608
  ]
}
