{
  "cid": 14664,
  "FAQ": {
    "": [],
    "1": [
      "『①：このカードがリンク召喚に成功した場合に発動できる。自分の墓地のサイバース族モンスターの種類（儀式・融合・S・X）の数だけこのカードにカウンターを置く』モンスター効果は誘発効果です。（対象を取る効果ではありません。）"
    ],
    "2": [
      "『②：このカードの攻撃力はバトルフェイズの間、このカードのカウンターの数×２５００アップする』モンスター効果は永続効果です。"
    ],
    "3": [
      "『③：相手がモンスターの効果を発動した時、このカードのカウンターを１つ取り除いて発動できる。その発動を無効にする。この効果をこのカードの攻撃宣言時からダメージステップ終了時までに発動した場合、このカードはもう１度続けて攻撃できる』モンスター効果は誘発即時効果です。（対象を取る効果ではありません。この効果を発動する際に、コストとして、このカードの効果で置かれているカウンターを1つ取り除きます。）",
      "『その発動を無効にする』モンスター効果は、相手のモンスター効果の発動に直接チェーンして発動する効果です。相手のモンスター効果の発動が行われたのであれば、メインフェイズやエンドフェイズなどでも発動する事ができます。その場合、『その発動を無効にする』処理のみが行われます。また、この効果が「ファイアウォール・ドラゴン・ダークフルード」自身の攻撃宣言時からダメージステップ終了時までの間に発動した場合には、『その発動を無効にする』処理に加えて、『発動した場合、このカードはもう１度続けて攻撃できる』処理も適用されます。"
    ]
  },
  "pendulumFAQ": []
}
