{
  "cid": 15586,
  "databaseDate": "2025-11-21",
  "FAQ": {
    "0": [],
    "1": [
      "【①の効果について】",
      "手札または墓地で発動できる起動効果です。",
      "この効果の発動時にコストとして、鳥獣族モンスター１体とドラゴン族モンスター１体、鳥獣族モンスター２体、ドラゴン族モンスター２体のいずれかを除外して発動できます。"
    ],
    "2": [
      "【②の効果について】",
      "モンスターゾーンで発動できる起動効果です。",
      "自分フィールドに装備カードが存在しない場合でも発動できます。",
      "効果が無効化されているモンスターや効果モンスター以外のモンスターを対象とすることもできます。（その場合でも処理を行います。）",
      "攻撃力が『自分フィールドの装備カードの数×１０００』より低いモンスターを対象とすることもできます。（その場合でも処理を行います。）"
    ],
    "3": [
      "【③の効果について】",
      "モンスターゾーンで発動できる誘発効果です。",
      "相手モンスターが戦闘で破壊され墓地へ送られたダメージステップ終了時に発動できます。"
    ]
  },
  "pendulumFAQ": {},
  "listedQAs": []
}
