{
  "cid": 16810,
  "FAQ": {
    "": [],
    "1": [
      "『①』は手札で発動できる起動効果です。（この効果を発動する際にコストとして、手札またはデッキから「<a href=\"faq_search.action?ope=4&cid=4007\">青眼の白龍</a>」１体を墓地へ送ります。）"
    ],
    "2": [
      "『②』はモンスターゾーンで発動できる起動効果です。",
      "『②』の効果の「<a href=\"faq_search.action?ope=4&cid=4007\">青眼の白龍</a>」のカード名が記されたカードとは、カードテキストに特定のカードのカード名として『「<a href=\"faq_search.action?ope=4&cid=4007\">青眼の白龍</a>」』と記載されたカードを指します。"
    ],
    "3": [
      "『③』は永続効果です。",
      "『③』の効果が適用されている状況でも、相手のモンスターが攻撃を行うかどうかを決定するのは相手プレイヤーです。攻撃を行う場合、その攻撃対象は相手ではなく自分が選択します。"
    ]
  },
  "pendulumFAQ": []
}
