{
  "cid": 17062,
  "FAQ": {
    "": [],
    "1": [
      "『①』は手札またはモンスターゾーンで発動できる誘発即時効果です。（相手がモンスターの効果を発動した時に、直接チェーンして発動できます。ダメージステップには発動できません。この効果を発動する際にコストとして、手札またはモンスターゾーンのこのカードを墓地へ送ります。）",
      "『①』の『「<a href=\"faq_search.action?ope=4&cid=15245\">アルバスの落胤</a>」を融合素材とする融合モンスター』とは、融合素材として「<a href=\"faq_search.action?ope=4&cid=15245\">アルバスの落胤</a>」のカード名が記載されている融合モンスターを指します。"
    ],
    "2": [
      "『②』は除外されたこのカードが発動できる誘発効果です。（ダメージステップでも発動できます。）",
      "『②』の『そのカード名が記されたモンスター』とは、テキストにカード名として「<a href=\"faq_search.action?ope=4&cid=15245\">アルバスの落胤</a>」と記されているモンスターを指します。"
    ]
  },
  "pendulumFAQ": []
}
