{
  "cid": 17356,
  "databaseDate": "2022-03-19",
  "FAQ": {
    "0": [
      "『EXデッキの裏側表示のこのカードは、融合召喚及び以下の方法でのみ特殊召喚できる。●融合モンスターを除く、EXモンスターゾーンと同じ縦列の自分のレベル５以上の「ヴァリアンツ」モンスター１体をリリースした場合に特殊召喚できる。』は効果として扱いません。（EXデッキの裏側表示のこのカードを特殊召喚する場合のみ、特殊召喚の方法が限定されます。）",
      "特殊召喚する際に、裏側守備表示のレベル５以上の「ヴァリアンツ」モンスターもリリースできます。",
      "『●』の方法で特殊召喚する際にチェーンブロックは作られません。その際の、モンスターのリリースとこのカードの特殊召喚は同時に行われません。",
      "エクストラモンスターゾーンに存在する該当のモンスターをリリースして特殊召喚することもできます。"
    ],
    "1": [
      "『①』はモンスターゾーンで発動できる誘発効果です。（ダメージステップでも発動できます。この効果を発動する際に、相手の魔法＆罠ゾーンの表側表示のモンスターカード１枚を対象に選択します。）",
      "『①』の『そのカードを持ち主の手札に戻し』の処理と、『その攻撃力分のダメージを相手に与える』処理は同時に行われたことになります。その後の『与えたダメージの半分だけこのカードの攻撃力をアップする』処理は同時に行われません。"
    ]
  },
  "pendulumFAQ": {
    "0": [],
    "1": [
      "『①』はペンデュラムゾーンで発動できるチェーンブロックの作られる効果です。（発動する際に『●』を１つ選択し、その『●』の効果として発動します。）"
    ]
  },
  "listedQAs": [
    7467,
    23611,
    23631
  ]
}
