{
  "cid": 18499,
  "databaseDate": "2023-01-14",
  "FAQ": {
    "0": [],
    "0.5": [
      "【『自分のフィールド・墓地の上記カードを除外した場合のみ特殊召喚できる』について】",
      "効果として扱いません。このモンスターをエクストラデッキから特殊召喚する手順です。",
      "この方法でしか特殊召喚できません。（融合召喚によって特殊召喚することはできません。）",
      "この方法で特殊召喚する際に、チェーンブロックは作られません。",
      "カードの除外とこのモンスターの特殊召喚は同時に行われません。",
      "裏側守備表示のカードも手順として除外できます。"
    ],
    "1": [
      "【①の効果について】",
      "モンスターゾーンで発動できる誘発効果です。",
      "この効果を発動する際に、このカード以外のモンスターゾーンのモンスター１体を対象に選択します（元々の攻撃力・守備力の数値を問わず対象に選択できます）。",
      "処理時に、『そのモンスターを破壊し』の処理を行い、破壊されたモンスターの元々の攻撃力か元々の守備力が０ではなかった場合、『その元々の攻撃力と元々の守備力の内、高い方の数値の半分だけこのカードの攻撃力をアップする』処理を行います。",
      "破壊の処理と攻撃力をアップする処理は同時に行われます。"
    ],
    "2": [
      "【②の効果について】",
      "モンスターゾーンで適用する永続効果です。"
    ]
  },
  "pendulumFAQ": {},
  "listedQAs": []
}
