{
  "cid": 19403,
  "FAQ": {
    "": [],
    "1": [
      "【①の効果について】",
      "モンスターゾーンで発動できる誘発効果です。"
    ],
    "2": [
      "【②の効果について】",
      "モンスターゾーンで発動できる起動効果です。",
      "処理時に、『そのカードを破壊し』の処理を行います。破壊に成功した場合、モンスターゾーンの表側表示のこのカードに『攻撃力を５００アップする』効果が適用されます。",
      "カードを破壊する処理と攻撃力をアップする処理は同時に行われたものとして扱います。",
      "この効果の適用後、このカードがモンスターゾーンに存在しなくなった場合、表側表示から裏側守備表示になった場合、このカードの効果が無効化された場合に、『攻撃力を５００アップする』効果の適用はなくなります。"
    ],
    "3": [
      "【③の効果について】",
      "誘発効果です。",
      "X素材を持っているこのカードが戦闘で破壊された場合、そのダメージステップ終了時に発動できます。",
      "X素材を持っているこのカードがダメージステップ中に効果で破壊された場合でも発動できます。",
      "このカードのエクシーズ召喚が無効になり、破壊された場合は発動できません。"
    ]
  },
  "pendulumFAQ": []
}
