{
  "cid": 19515,
  "FAQ": {
    "": [],
    "1": [
      "【①の効果について】",
      "魔法＆罠ゾーンで適用するチェーンブロックの作られない効果です。"
    ],
    "2": [
      "【②の効果について】",
      "魔法＆罠ゾーンで適用できるチェーンブロックの作られない効果です。",
      "通常召喚とこの効果による召喚が両方行える場合、どちらから先に行っても構いません。",
      "この効果で召喚を行う際に、チェーンブロックは作られません。",
      "この効果による召喚を行う際には、この効果によって召喚を行うことを相手に伝えます。",
      "“通常召喚に加えて召喚を行う効果”が複数適用されている場合でも、そのターン中にはそれらの効果のうち１つしか適用できません。（１つを適用した場合、そのターンには他の“通常召喚に加えて召喚を行う効果”を適用できません。）"
    ],
    "3": [
      "【③の効果について】",
      "魔法＆罠ゾーンで発動できるチェーンブロックの作られる効果です。",
      "この効果を発動する際に、対象として自分のモンスターゾーンに表側表示で存在する、レベルを持つ「ゴブリン」モンスター２体を選択します。また、この効果を発動する際に●を１つ選択し、その効果として発動します。【１つ目の●の効果について】",
      "処理時に、対象のモンスターの両方がモンスターゾーンに表側表示で存在する場合、対象のモンスターの内１体に『もう１体のレベルと同じにする』効果を適用します。",
      "この効果を適用したモンスターがモンスターゾーンに存在しなくなった場合、表側表示から裏側守備表示になった場合に、『もう１体のレベルと同じにする』効果の適用はなくなります。"
    ],
    "3.5": [
      "【②つ目の●の効果について】",
      "処理時に、対象のモンスターの両方がモンスターゾーンに表側表示で存在する場合、対象のモンスター２体に『レベルは、それぞれの元々のレベルを合計したレベルになる』効果を適用します。",
      "この効果を適用したモンスターがモンスターゾーンに存在しなくなった場合、表側表示から裏側守備表示になった場合に、そのモンスターに対する『それぞれの元々のレベルを合計したレベルになる』効果の適用はなくなります。"
    ]
  },
  "pendulumFAQ": []
}
