{
  "cid": 20180,
  "databaseDate": "2024-04-27",
  "FAQ": {
    "0": [],
    "1": [
      "【①の効果について】",
      "手札で発動できる起動効果です。"
    ],
    "2": [
      "【②の効果について】",
      "魔法＆罠ゾーンで永続魔法カード扱いのこのカードが発動できるチェーンブロックの作られる効果です。",
      "自分メインフェイズに発動できます。(スペルスピード１の永続魔法カードの効果として扱います。)",
      "処理時に、『このカードを特殊召喚する』処理を行います。特殊召喚に成功した場合、その後、『デッキから「千年」モンスターか「ミレニアム」モンスター１体を手札に加える』処理を行うことができます。",
      "特殊召喚する処理と手札に加える処理を両方行う場合、それらは同時に行われません。"
    ],
    "3": [
      "【③の効果について】",
      "モンスターゾーンで適用する永続効果です。"
    ]
  },
  "pendulumFAQ": {},
  "listedQAs": []
}
