{
  "cid": 20949,
  "databaseDate": "2024-10-21",
  "FAQ": {
    "0": [],
    "1": [
      "【①の効果について】",
      "処理時に、『自分の手札・フィールドのモンスターを融合素材とし』の処理を行います。その後、『融合モンスター１体を融合召喚する』処理を行います。融合召喚に成功した場合、その後、『自分の手札・フィールドのモンスターを融合素材とし』の処理を行い、その後、『融合モンスター１体を融合召喚する』処理を行うことができます。",
      "１度目の素材とする処理、１度目の融合召喚する処理、２度目の素材とする処理、２度目の融合召喚する処理は全て同時に行われません。",
      "素材となったモンスターは、他の効果が適用されていない限り、墓地へ送られます。ただし、他の効果の適用により融合素材が墓地へ送られなかった場合でも、手札・フィールドを離れたのであれば、融合モンスターの特殊召喚は行われます。"
    ]
  },
  "pendulumFAQ": {},
  "listedQAs": []
}
