{
  "cid": 21440,
  "databaseDate": "2025-04-26",
  "FAQ": {
    "0": [],
    "0.5": [
      "【『このカード名はルール上「ハングリーバーガー」として扱う』について】",
      "効果として扱いません。（効果が無効化されている状況でも「ハングリーバーガー」として扱います。）",
      "「ハングリーバーガー」と「アングリーバーガー」を合わせて３枚までしかデッキ構築に使用できません。"
    ],
    "1": [
      "【①の効果について】",
      "手札で発動できる起動効果です。",
      "処理時に、『デッキから「ヌーベルズ」モンスター１体を手札に加え』の処理を行い、手札に加えた場合、『このカードをデッキに戻す』処理を行います。",
      "手札に加える処理とデッキに戻す処理は同時に行われる扱いです。"
    ],
    "2": [
      "【②の効果について】",
      "モンスターゾーンで適用する永続効果です。",
      "相手のモンスターに適用される効果です。"
    ],
    "3": [
      "【③の効果について】",
      "モンスターゾーンで発動できる誘発即時効果です。",
      "ダメージステップには発動できません。",
      "処理時に、『自分・相手フィールドの攻撃表示モンスター１体をリリースし』の処理を行い、リリースした場合、『手札・デッキから攻撃力２０００の「ハングリーバーガー」１体を特殊召喚する』処理を行います。",
      "リリースする処理と特殊召喚する処理は同時に行われる扱いです。"
    ]
  },
  "pendulumFAQ": {},
  "listedQAs": [
    277
  ]
}
