{
  "cid": 21471,
  "databaseDate": "2025-04-26",
  "FAQ": {
    "0": [],
    "1": [
      "【①の効果について】",
      "このカードの発動時の効果です。",
      "処理時に、『自分のフィールド・墓地のサイキック族モンスターを融合素材として除外し』の処理を行います。その後、『サイキック族の融合モンスター１体を融合召喚する』処理を行います。",
      "素材とする処理と融合召喚する処理は同時に行われません。",
      "素材となったモンスターは、他の効果が適用されていない限り除外されます。ただし、他の効果の適用により融合素材が除外されなかった場合でも、素材としたところから離れたのであれば、融合モンスターの特殊召喚は行われます。"
    ],
    "2": [
      "【②の効果について】",
      "墓地で発動できるチェーンブロックの作られる効果です。",
      "ダメージステップでも発動できます。"
    ]
  },
  "pendulumFAQ": {},
  "listedQAs": []
}
