{
  "cid": 22076,
  "databaseDate": "2026-06-26",
  "FAQ": {
    "0": [],
    "1": [
      "【①の効果について】",
      "このカードの発動時の効果です。",
      "このカードを発動する際に、自分の墓地のレベル３以上の「R.B.」モンスター１体を対象に選択することができます。対象を選択せずに発動した場合、この効果処理は適用されません。"
    ],
    "2": [
      "【②の効果について】",
      "魔法＆罠ゾーンで発動できるチェーンブロックの作られる効果です。",
      "自分メインフェイズに発動できます。",
      "処理時に、『そのモンスターの元々の攻撃力の合計分だけ自分のLPを回復し』の処理を行い、回復する処理に成功した場合、『そのモンスターを手札・EXデッキに戻す』処理を行います。１体以上手札・エクストラデッキに戻すことに成功した場合、その後、『手札から「R.B.」モンスター１体を特殊召喚』する処理を行うことができます。",
      "回復する処理と手札・エクストラデッキに戻す処理は同時に行われる扱いです。",
      "手札・エクストラデッキに戻す処理と特殊召喚する処理を両方行う場合、それらは同時に行われません。"
    ]
  },
  "pendulumFAQ": {},
  "listedQAs": []
}
