{
  "cid": 22560,
  "databaseDate": "2026-01-23",
  "FAQ": {
    "0": [],
    "1": [
      "【①の効果について】",
      "モンスターゾーンで適用する永続効果です。",
      "召喚（通常召喚のうち手札のモンスターを攻撃表示でフィールドに出すこと）の際のリリースをなくすことができる効果です。この効果を適用してモンスターをセットすることはできません。"
    ],
    "2": [
      "【②の効果について】",
      "モンスターゾーンで発動できる誘発即時効果です。",
      "この効果のチェーンブロックの処理後、ただちに『レベル５以上の闇属性モンスター１体の召喚』を行います。"
    ],
    "3": [
      "【③の効果について】",
      "モンスターゾーンで発動できる誘発効果です。",
      "処理時に、『手札のモンスターを任意の数だけ相手に見せ、好きな順番でデッキの下に戻す』処理を行い、１枚以上デッキの下に戻した場合、その後、『自分は戻した数だけドローする』処理を行います。",
      "デッキの下に戻す処理とドローする処理は同時に行われません。"
    ]
  },
  "pendulumFAQ": {},
  "listedQAs": [
    16986,
    22383
  ]
}
