{
  "cid": 22999,
  "databaseDate": "2026-04-24",
  "FAQ": {
    "0": [],
    "1": [
      "【①の効果について】",
      "フィールドゾーンで適用するチェーンブロックの作られない効果です。"
    ],
    "2": [
      "【②の効果について】",
      "フィールドゾーンで発動できるチェーンブロックの作られる効果です。",
      "処理時に、『「機獣トークン」（機械族・地・星６・攻／守２０００）１体を特殊召喚し』の処理を行い、特殊召喚に成功した場合、『デッキから「ブリッツクリーク」モンスター１体を手札に加える』処理を行います。",
      "特殊召喚する処理と手札に加える処理は同時に行われる扱いです。"
    ],
    "3": [
      "【③の効果について】",
      "墓地で発動できるチェーンブロックの作られる効果です。",
      "ダメージステップには発動できません。"
    ]
  },
  "pendulumFAQ": {},
  "listedQAs": []
}
