{
  "cid": 23355,
  "databaseDate": "2026-07-17",
  "FAQ": {
    "0": [],
    "1": [
      "【①の効果について】",
      "手札で発動できる起動効果です。"
    ],
    "2": [
      "【②の効果について】",
      "モンスターゾーンで発動できる起動効果です。",
      "エクストラデッキに表側で加わっているエクシーズ/ペンデュラムモンスターを見せてこの効果を発動することもできます。",
      "処理時に、このカードまたは対象のカードがフィールドに存在しなくなった場合、処理は何も行われません。"
    ],
    "3": [
      "【③の効果について】",
      "墓地で発動できる起動効果です。",
      "処理時に、『自分フィールドのX素材を１つ取り除く』処理を行います。取り除く処理に成功した場合、その後、『自分の手札・墓地から攻撃力か守備力が０のモンスター１体を特殊召喚』する処理を行うことができます。",
      "取り除く処理と特殊召喚する処理を両方行う場合、それらは同時には行われません。"
    ]
  },
  "pendulumFAQ": {},
  "listedQAs": [
    23215
  ]
}
