{
  "cid": 5231,
  "databaseDate": "2020-12-19",
  "FAQ": {
    "0": [],
    "1": [
      "『①』はチェーンブロックの作られない効果です。（このカードの発動時の処理が完了したのち、この効果を適用して罠カードを発動できるようになります。）"
    ],
    "2": [
      "『②』はフィールドで発動できるチェーンブロックの作られる効果です。（自分のメインフェイズに発動できる効果です。対象を取る効果ではありません。この効果を発動する際にコストとして、自分のモンスターゾーンの表側表示の「聖獣セルケト」１体とこのカードを墓地へ送ります。）",
      "『②』の効果でエクストラデッキから融合モンスターを特殊召喚することができます。ただし、その特殊召喚は融合召喚として扱いません。（融合召喚でしか特殊召喚できない融合モンスターを、この効果で特殊召喚することはできません。）"
    ]
  },
  "pendulumFAQ": {},
  "listedQAs": [
    14553,
    14554,
    14555,
    14556,
    14557,
    14558,
    14559,
    14560,
    14561,
    14562,
    14563,
    14564,
    14565,
    14566,
    14567,
    15960,
    23926,
    23945,
    24152
  ]
}
