{
  "cid": 5381,
  "databaseDate": "2020-04-01",
  "FAQ": {
    "0": [
      "『召喚・リバースしたターンのエンドフェイズ時に持ち主の手札に戻る』モンスター効果は、フィールドで発動する誘発効果です。（対象を取る効果ではありません。「阿修羅」自身が召喚・リバースしたターンのエンドフェイズに1度、必ず発動する効果です。）",
      "『このカードは相手フィールド上に存在する全てのモンスターに１回ずつ攻撃をする事ができる』モンスター効果は永続効果です。",
      "『このカードは相手フィールド上に存在する全てのモンスターに１回ずつ攻撃をする事ができる』モンスター効果によって、モンスターに攻撃を行った後、プレイヤーへの直接攻撃を行う事はできません。また、プレイヤーへの直接攻撃を行った後、『このカードは相手フィールド上に存在する全てのモンスターに１回ずつ攻撃をする事ができる』モンスター効果によって、モンスターに攻撃を行う事はできません。"
    ]
  },
  "pendulumFAQ": {},
  "listedQAs": [
    136,
    8182,
    12701,
    19320
  ]
}
