{
  "cid": 5428,
  "databaseDate": "2020-04-01",
  "FAQ": {
    "0": [
      "『このカードは通常召喚できない。「大神官デ・ザード」の効果で特殊召喚する事ができる』は効果として扱いません。（手札・デッキから「大神官デ・ザード」のモンスター効果によって特殊召喚されます。）",
      "「大神官デ・ザード」のモンスター効果によって特殊召喚に成功した後に墓地へ送られているのであれば、「死者蘇生」の効果によって墓地から特殊召喚する事ができます。",
      "『このカードは１ターンに１度だけ裏側守備表示にする事ができる』モンスター効果は、フィールドで発動する起動効果です。（対象を取る効果ではありません。）",
      "『このカードがリバースした時、自分の墓地に存在するアンデット族モンスター１体を選択して特殊召喚する事ができる』モンスター効果は、フィールドで発動する誘発効果です。（自分の墓地のアンデット族モンスター1体を対象に取る効果です。「不死王リッチー」自身がリバースした場合に、任意に発動する事ができる効果です。ダメージステップでも発動する事ができます。）",
      "『フィールド上に表側表示で存在するこのカードを対象とする魔法・罠カードが発動した時、その発動を無効にし破壊する』モンスター効果は、フィールドで発動する誘発即時効果です。（対象を取る効果ではありません。「不死王リッチー」自身を対象として発動した魔法・罠カードのカードの発動に直接チェーンして必ず発動する効果です。ダメージステップでも発動します。）"
    ]
  },
  "pendulumFAQ": {},
  "listedQAs": []
}
