{
  "cid": 5830,
  "databaseDate": "2015-03-12",
  "FAQ": {
    "0": [
      "『このカードは通常召喚できない。自分の墓地の水属性モンスター２体をゲームから除外して特殊召喚する』は効果の扱いではありません。特殊召喚モンスターの特殊召喚の手順となります。（特殊召喚の手順として墓地の水属性モンスター２体を除外しますので、除外する事と、特殊召喚は同時に行われる扱いではありません。）",
      "特殊召喚に成功した「フェンリル」がその後に墓地へ送られた場合、「死者蘇生」の効果によって墓地から特殊召喚する事ができます。",
      "『このカードが戦闘によって相手モンスターを破壊した場合、次の相手ターンのドローフェイズをスキップする』効果は誘発効果です。（対象を取る効果ではありません。ダメージステップ終了時に発動する効果です。）",
      "「フェンリル」が同じ攻撃力のモンスターと戦闘を行い、互いに破壊される場合には効果を発動する事はできません。"
    ]
  },
  "pendulumFAQ": {},
  "listedQAs": [
    6113,
    12097
  ]
}
