{
  "cid": 6727,
  "databaseDate": "2018-03-22",
  "FAQ": {
    "0": [
      "「サイバー・ダイナソー」のモンスター効果は、手札にて発動する誘発効果です。（対象を取る効果ではありません。）",
      "ダメージステップに発動する事はできません。",
      "相手プレイヤーが手札のモンスターの特殊召喚に成功した時に、任意に発動する事ができる効果です。（相手プレイヤーが手札のモンスターの特殊召喚に成功したのであれば、自分のターンだけでなく、相手のターンでも発動する事ができます。）",
      "チェーン2以降に発動したカードの効果によって、相手プレイヤーが手札のモンスターの特殊召喚に成功した場合には、「サイバー･ダイナソー」のモンスター効果を発動する事はできません。",
      "「サイバー･ダイナソー」は通常召喚モンスターです。（手札やデッキから墓地へ送られているような場合でも、「死者蘇生」の効果で特殊召喚する事はできます。）"
    ]
  },
  "pendulumFAQ": {},
  "listedQAs": [
    12925
  ]
}
