{
  "cid": 7174,
  "databaseDate": "2016-06-23",
  "FAQ": {
    "0": [],
    "0.5": [
      "【『このカード名はルール上「N・アクア・ドルフィン」としても扱う』について】",
      "効果として扱いません（このカードの効果が無効化されている状況でも、このカードは「N・アクア・ドルフィン」として扱われます）。",
      "このカードと「N・アクア・ドルフィン」は、合計３枚までしかデッキに使用できません。"
    ],
    "0.75": [
      "【『このカードは「NEX」の効果でのみ特殊召喚できる』について】",
      "効果として扱いません。"
    ],
    "1": [
      "【①の効果について】",
      "モンスターゾーンで発動できる起動効果です。",
      "確認した相手の手札にモンスターがなかった場合や、選んだモンスターの攻撃力以上の攻撃力を持つモンスターが自分フィールドに存在しない場合、そこで効果処理を完了します。",
      "選んだモンスターの攻撃力以上の攻撃力を持つモンスターが自分フィールドに存在する場合、『選んだモンスターを破壊し』の処理を行い、『相手に５００ダメージを与える』処理を行います。これらの処理は同時に行われます。"
    ]
  },
  "pendulumFAQ": {},
  "listedQAs": [
    9064,
    12622,
    12775,
    13157,
    13158,
    17047,
    18073,
    18612,
    19063,
    20704
  ]
}
