{
  "cid": 7409,
  "databaseDate": "2022-02-19",
  "FAQ": {
    "0": [],
    "1": [
      "『①』はモンスターゾーンで適用される永続効果です。"
    ],
    "2": [
      "『②』はモンスターゾーンで発動する誘発効果です。（必ず発動する効果です。攻撃表示のこのカードが攻撃対象に選択された戦闘のダメージ計算前に発動します。）"
    ],
    "3": [
      "『③』はモンスターゾーンで発動する誘発効果です。（自分のエンドフェイズごとに、必ず発動する効果です。）"
    ],
    "4": [
      "『④』は破壊されたこのカードが発動できる誘発効果です。（ダメージステップでも発動できます。）",
      "『④』はこのカードが破壊された直後にのみ発動できる効果です。チェーン２以降で発動した効果によって破壊された場合など、このカードが破壊された後に別の処理が続いた場合には、この効果を発動できません。"
    ]
  },
  "pendulumFAQ": {},
  "listedQAs": [
    12844,
    13344,
    24033,
    24041,
    24055,
    24058
  ]
}
