{
  "cid": 7611,
  "databaseDate": "2016-01-21",
  "FAQ": {
    "0": [
      "『このカードのカード名は、墓地に存在する限り「ワイト」として扱う』効果は、起動効果・誘発効果・誘発即時効果・永続効果のいずれにも分類されない効果です。",
      "『このカードがフィールド上に表側表示で存在する限り、「ワイト夫人」以外のフィールド上のレベル３以下のアンデット族モンスターは戦闘では破壊されず、魔法・罠カードの効果も受けない』効果は永続効果です。",
      "『「ワイト夫人」以外のフィールド上のレベル３以下のアンデット族モンスターは戦闘では破壊されず、魔法・罠カードの効果も受けない』効果は、自分のモンスターゾーンに表側表示で存在するレベル3以下のアンデット族モンスターだけでなく、相手のモンスターゾーンに表側表示で存在するレベル3以下のアンデット族モンスターにも適用される効果です。"
    ]
  },
  "pendulumFAQ": {},
  "listedQAs": [
    24254
  ]
}
