{
  "cid": 8015,
  "databaseDate": "2022-05-20",
  "FAQ": {
    "0": [],
    "1": [
      "【①の効果について】",
      "『このカードは表示形式によって以下の効果を得る。』は効果として扱いません。",
      "『●攻撃表示』の効果と『●守備表示』の効果は、１ターン中にそれぞれ１度ずつ発動できます。"
    ],
    "1.5": [
      "【『●攻撃表示』の効果について】",
      "モンスターゾーンで適用する永続効果です。",
      "自分のモンスターゾーンの表側表示の全ての「D」モンスターに適用される効果です。"
    ],
    "1.75": [
      "【『●守備表示』の効果について】",
      "モンスターゾーンで適用する永続効果です。",
      "このモンスター以外の、自分のモンスターゾーンの全ての「D」モンスターに適用される効果です。"
    ]
  },
  "pendulumFAQ": {},
  "listedQAs": []
}
