{
  "cid": 8142,
  "databaseDate": "2017-06-08",
  "FAQ": {
    "0": [
      "『このカードが自分フィールド上に表側表示で存在する限り、相手フィールド上にモンスターが特殊召喚される度に、その時に特殊召喚されたモンスターにAカウンターを１つ置く』モンスター効果は永続効果です。（Aカウンターを置く処理が適用される際にチェーンブロックは作られません。）",
      "相手のモンスターゾーンに複数体のモンスターが同時に特殊召喚された場合には、それぞれの特殊召喚されたモンスターにAカウンターが1つずつ置かれます。",
      "『Aカウンターが乗ったモンスターは、「エーリアン」と名のついたモンスターと戦闘する場合、Aカウンター１つにつき攻撃力と守備力が３００ポイントダウンする』モンスター効果は永続効果です。",
      "「エーリアン・キッズ」が2体存在する場合、ダメージ計算時にのみ、それぞれの『「エーリアン」と名のついたモンスターと戦闘する場合、Aカウンター１つにつき攻撃力と守備力が３００ポイントダウンする』効果が適用されます。"
    ]
  },
  "pendulumFAQ": {},
  "listedQAs": []
}
