{
  "cid": 8690,
  "databaseDate": "2019-01-28",
  "FAQ": {
    "0": [
      "「グレイモヤ不発弾」のカードの発動は、ダメージステップ以外であればいつでも行う事ができます。",
      "「グレイモヤ不発弾」のカードの発動の際に、自分及び相手のモンスターゾーンに表側表示で存在するモンスターの中から合計2体を対象に取って発動します。（選択したモンスターを対象に取り続ける効果です。）",
      "『選択したモンスターがフィールド上から離れた時、このカードを破壊する』処理にチェーンブロックは作られません。（対象のモンスター2体の内1体がフィールドから離れた場合にも適用されます。また、ダメージステップでも適用されます。）",
      "『このカードが破壊された時、選択したモンスターを破壊する』処理にチェーンブロックは作られません。（「グレイモヤ不発弾」が他のカードの効果で破壊される場合だけでなく、「グレイモヤ不発弾」自身の効果処理によって破壊される場合にも適用されます。また、ダメージステップでも適用されます。）"
    ]
  },
  "pendulumFAQ": {},
  "listedQAs": [
    9419,
    9420
  ]
}
