{
  "cid": 8822,
  "databaseDate": "2019-03-07",
  "FAQ": {
    "0": [
      "「ZERO－MAX」は手札から発動する事はできません。自分のターンのメインフェイズ1にて、自分の手札が0枚の場合に、魔法＆罠ゾーンにセットされている「ZERO－MAX」を裏から表にして発動する事になります。",
      "自分の墓地に存在する「インフェルニティ」と名のついたモンスター1体を対象に取る効果です。",
      "『選択したモンスターを特殊召喚し』の処理と、『特殊召喚したモンスターの攻撃力より低い攻撃力を持つ、フィールド上に表側表示で存在するモンスターを全て破壊する』処理は同時に行われる扱いではありません。",
      "『このカードを発動するターン、自分はバトルフェイズを行う事ができない』は効果の扱いではありません。",
      "効果処理時に自分の手札が0枚でなくなっている場合でも、効果処理は通常通り適用されます。"
    ]
  },
  "pendulumFAQ": {},
  "listedQAs": [
    192
  ]
}
