{
  "cid": 9150,
  "databaseDate": "2015-12-24",
  "FAQ": {
    "0": [],
    "0.5": [
      "【『自分フィールド上に存在する「スクラップ」と名のついたモンスターが破壊され墓地へ送られた時に発動する事ができる。フィールド上に表側表示で存在する魔法・罠カードを全て破壊する』効果について】",
      "対象を取る効果ではありません。",
      "ダメージステップには発動できません。（「スクラップ」モンスターが戦闘で破壊され墓地へ送られた場合には発動できません。）",
      "自分のモンスターゾーンに表側表示で存在する「スクラップ」モンスターが破壊され墓地へ送られた時に発動できます。（自分のモンスターゾーンに裏側守備表示で存在する「スクラップ」モンスターが破壊され墓地へ送られた時には発動できません。）",
      "チェーン２以降で発動した効果によって「スクラップ」モンスターが破壊され墓地へ送られた場合など、「スクラップ」モンスターが破壊され墓地へ送られた後に別の処理が続いた場合には、この効果を発動できません。"
    ]
  },
  "pendulumFAQ": {},
  "listedQAs": []
}
