{
  "cid": 9194,
  "databaseDate": "2018-02-22",
  "FAQ": {
    "0": [
      "『１ターンに１度、このカードに装備カードが装備された時、相手ライフに８００ポイントダメージを与える』モンスター効果は誘発効果です。（対象を取る効果ではありません。）",
      "『相手ライフに８００ポイントダメージを与える』モンスター効果は、「セブン・ソード・ウォリアー」自身に装備カードが装備された場合に必ず発動する効果です。（ダメージステップでも発動します。）",
      "『１ターンに１度、このカードに装備された装備カード１枚を墓地へ送る事ができる』モンスター効果は起動効果です。（「セブン・ソード・ウォリアー」自身に装備されている装備魔法カード1枚を対象に取る効果です。）",
      "『このカードに装備された装備カードが墓地へ送られた時、相手フィールド上に表側表示で存在するモンスター１体を選択して破壊する事ができる』モンスター効果は誘発効果です。（相手のモンスターゾーンに表側表示で存在するモンスター1体を対象に取る効果です。ダメージステップに発動する事はできません。）"
    ]
  },
  "pendulumFAQ": {},
  "listedQAs": [
    10314
  ]
}
