{
  "cid": 9194,
  "databaseDate": "2018-02-22",
  "FAQ": {
    "0": [],
    "0.5": [
      "【『１ターンに１度、このカードに装備カードが装備された時、相手ライフに８００ポイントダメージを与える』効果について】",
      "モンスターゾーンで発動する誘発効果です。",
      "条件を満たした場合、必ず発動します。",
      "ダメージステップでも発動します。"
    ],
    "0.75": [
      "【『１ターンに１度、このカードに装備された装備カード１枚を墓地へ送る事ができる』効果について】",
      "モンスターゾーンで発動できる起動効果です。"
    ],
    "0.875": [
      "【『このカードに装備された装備カードが墓地へ送られた時、相手フィールド上に表側表示で存在するモンスター１体を選択して破壊する事ができる』効果について】",
      "モンスターゾーンで発動できる誘発効果です。",
      "ダメージステップには発動できません。",
      "相手フィールドに表側表示で存在するモンスター１体を対象に取る効果です。",
      "このカードに装備された装備カードが墓地へ送られた直後にのみ発動できます。チェーン２以降で発動した効果によってこのカードに装備された装備カードが墓地へ送られたなどの理由で、このカードに装備された装備カードが墓地へ送られた後に別の処理が行われた場合、この効果は発動できません。"
    ]
  },
  "pendulumFAQ": {},
  "listedQAs": []
}
