{
  "cid": 9555,
  "databaseDate": "2017-06-15",
  "FAQ": {
    "0": [],
    "0.5": [
      "【『アドバンス召喚したこのカードがフィールド上から墓地へ送られた時、デッキからレベル４以下のモンスター１体を手札に加える事ができる』効果について】",
      "墓地で発動できる誘発効果です。",
      "ダメージステップでも発動できます。",
      "アドバンス召喚したこのカードがモンスターゾーンから墓地へ送られた直後に、任意に発動できる効果です。チェーン２以降で発動した効果によって墓地へ送られた場合など、このカードが墓地へ送られた後に別の処理が続いた場合には、発動できません。",
      "自分のデッキにレベル４以下のモンスターが存在しない場合には発動できません。",
      "アドバンス召喚したこのカードが裏側守備表示になったのちに墓地へ送られた時や、一時的に除外されモンスターゾーンに戻ったのちに墓地へ送られた時でも発動できます。"
    ]
  },
  "pendulumFAQ": {},
  "listedQAs": [
    12616
  ]
}
