{
  "cid": 9676,
  "databaseDate": "2012-07-20",
  "FAQ": {
    "0": [
      "ダメージステップ中に発動する事はできません。",
      "エクシーズモンスターを対象に選択して、発動する事はできません。",
      "対象に選択したモンスターのレベルは、そのモンスターが表側表示で存在する限り適用されます。",
      "対象に選択したモンスターが裏側表示になる等した場合、レベルは元に戻ります。"
    ]
  },
  "pendulumFAQ": {},
  "listedQAs": [
    6060,
    6785,
    7983,
    8772,
    9015,
    10466,
    12334,
    12402,
    13705,
    14386,
    14389,
    14653,
    14765,
    15137,
    15501,
    15715,
    15725,
    15921,
    16228,
    16884,
    17327,
    17695,
    17759,
    18835,
    19276,
    19668,
    20169,
    20252,
    21017,
    21747,
    22200,
    22351,
    22375,
    22455
  ]
}
